module_warehouse/__init__.py
module_warehouse/navigation.py
module_warehouse/urls.py
module_warehouse/views.py
module_warehouse/templates/module_warehouse/warehouse_modules.html
module_warehouse-0.2.dist-info/LICENSE
module_warehouse-0.2.dist-info/METADATA
module_warehouse-0.2.dist-info/WHEEL
module_warehouse-0.2.dist-info/top_level.txt
module_warehouse-0.2.dist-info/RECORD
