Metadata-Version: 2.1
Name: module-warehouse
Version: 0.2
Summary: plugin which displays modules stored in warehouse
Home-page: UNKNOWN
Author: Viktor Kubec
Author-email: Viktor.Kubec@gmail.com
License: UNKNOWN
Platform: UNKNOWN
License-File: LICENSE
